bio2bel_reactome/__init__.py
bio2bel_reactome/__main__.py
bio2bel_reactome/cli.py
bio2bel_reactome/constants.py
bio2bel_reactome/enrich.py
bio2bel_reactome/manager.py
bio2bel_reactome/models.py
bio2bel_reactome/to_belns.py
bio2bel_reactome/utils.py
bio2bel_reactome/web.py
bio2bel_reactome/parsers/__init__.py
bio2bel_reactome/parsers/entity_pathways.py
bio2bel_reactome/parsers/pathway_hierarchy.py
bio2bel_reactome/parsers/pathway_names.py
bio2bel_reactome-0.2.0.dist-info/LICENSE
bio2bel_reactome-0.2.0.dist-info/METADATA
bio2bel_reactome-0.2.0.dist-info/WHEEL
bio2bel_reactome-0.2.0.dist-info/entry_points.txt
bio2bel_reactome-0.2.0.dist-info/top_level.txt
bio2bel_reactome-0.2.0.dist-info/RECORD
