Metadata-Version: 2.1
Name: bio2bel-reactome
Version: 0.2.0
Summary: A wrapper around Reactome RESTful API
Home-page: https://github.com/bio2bel/reactome
Author: Daniel Domingo-Fernández and Charles Tapley Hoyt
Author-email: daniel.domingo.fernandez@scai.fraunhofer.de
Maintainer: Daniel Domingo-Fernández and Charles Tapley Hoyt
Maintainer-email: daniel.domingo.fernandez@scai.fraunhofer.de
License: MIT License
Keywords: Biological Expression Language,BEL,Reactome,Systems Biology,Networks Biology
Platform: UNKNOWN
Classifier: Development Status :: 4 - Beta
Classifier: Environment :: Console
Classifier: Intended Audience :: Developers
Classifier: Intended Audience :: Science/Research
Classifier: License :: OSI Approved :: MIT License
Classifier: Operating System :: OS Independent
Classifier: Programming Language :: Python
Classifier: Programming Language :: Python :: 3 :: Only
Classifier: Programming Language :: Python :: 3.6
Classifier: Programming Language :: Python :: 3.7
Classifier: Topic :: Scientific/Engineering :: Bio-Informatics
Requires-Dist: click
Requires-Dist: bio2bel (<0.3.0,>=0.2.0)
Requires-Dist: compath-utils (>=0.1.0)
Requires-Dist: bio2bel-hgnc (>=0.1.0)
Requires-Dist: bio2bel-chebi (>=0.1.0)
Requires-Dist: pybel (<0.13.0,>=0.12.0)
Requires-Dist: sqlalchemy
Requires-Dist: pandas
Requires-Dist: tqdm
Requires-Dist: flask
Requires-Dist: flask-admin
Provides-Extra: docs
Requires-Dist: sphinx; extra == 'docs'
Requires-Dist: sphinx-rtd-theme; extra == 'docs'
Requires-Dist: sphinx-click; extra == 'docs'
Provides-Extra: web
Requires-Dist: flask; extra == 'web'
Requires-Dist: flask-admin; extra == 'web'
